model_w/docker/__init__.py
model_w/docker/__main__.py
model_w/docker/build.py
model_w/docker/config.py
model_w/docker/exceptions.py
model_w/docker/install.py
model_w/docker/output.py
model_w/docker/platform.py
model_w/docker/py.typed
model_w/docker/run.py
model_w/docker/serve.py
modelw_docker-2025.7.0.dist-info/LICENSE
modelw_docker-2025.7.0.dist-info/METADATA
modelw_docker-2025.7.0.dist-info/WHEEL
modelw_docker-2025.7.0.dist-info/entry_points.txt
modelw_docker-2025.7.0.dist-info/RECORD
