Metadata-Version: 2.3
Name: modelw-docker
Version: 2025.7.0
Summary: Utility to simplify Dockerfiles
License: WTFPL
Keywords: docker,django,nuxt,dockerfile
Author: Rémy Sanchez
Author-email: remy.sanchez@hyperthese.net
Requires-Python: >=3.13,<4.0
Classifier: Development Status :: 3 - Alpha
Classifier: Environment :: Console
Classifier: Framework :: Django
Classifier: Framework :: Wagtail
Classifier: Intended Audience :: Developers
Classifier: License :: Other/Proprietary License
Classifier: Programming Language :: Python :: 3
Classifier: Programming Language :: Python :: 3.13
Classifier: Topic :: Software Development :: Build Tools
Classifier: Topic :: Utilities
Requires-Dist: colorama (>=0.4.6,<0.5.0)
Requires-Dist: psutil (>=5.9.5,<6.0.0)
Requires-Dist: setuptools
Requires-Dist: typefit (>=1.0.0,<2.0.0)
Project-URL: Documentation, https://github.com/ModelW/docker/
Project-URL: Homepage, https://github.com/ModelW/docker/
Project-URL: Repository, https://github.com/ModelW/docker/
